{"app_exclusive_code.md":"2b63715e","app_exclusive_image.md":"14ef28d3","app_exclusive_audio.md":"4acaf9e3","app_exclusive_media.md":"fd6b67e5","guide_advanced_optional-cfg-1.md":"4319c1f2","app_exclusive_video.md":"5a2e4df0","app_common_android.md":"b4af4ea4","guide_advanced_beauty-1.md":"48591bf5","guide_advanced_beauty-2.md":"c94ca3fa","guide_advanced_debug.md":"e26e67f3","guide_advanced_make-install-disk.md":"5b519a04","guide_rookie_pre-install.md":"1bcb9462","guide_advanced_optional-cfg-2.md":"0252d6ba","guide_advanced_power-ctl.md":"bc03d334","guide_advanced_system-ctl.md":"aa2dd493","guide_rookie_basic-install-detail.md":"9a5d10a4","guide_rookie_basic-install.md":"b6f4dfbd","app_common_collaboration.md":"232dedb4","guide_rookie_desktop-env-and-app.md":"5daf869f","app_common_communication.md":"24fb6052","guide_rookie_graphic-driver.md":"efb5fa37","postscript_contribute.md":"f3a9ff59","guide_rookie_pre-virt.md":"ba816148","app_common_daily.md":"9c0a646e","guide_rookie_transparent.md":"f8e56b87","app_common_media.md":"813eb612","app_common_office.md":"20859143","postscript_copyright.md":"84133590","app_common_play.md":"219831b2","app_common_remote.md":"6ce86257","guide_index.md":"5808a881","guide_prepare_head-on-blow.md":"c045fddf","guide_prepare_understand.md":"ecbfbb39","guide_advanced_btrfs.md":"bdd767cc","postscript_about.md":"5707f0ef","guide_advanced_beauty-3.md":"a444ca6c","postscript_contributor-covenant.md":"dbb166e9","postscript_postscript.md":"3f2b2165","index.md":"1d98d5ec"}
